src/__init__.py
src/cryptolation.py
src/information/__init__.py
src/node_utilities/__init__.py
src/node_utilities/node_utils.py
src/output_routing/__init__.py
src/output_routing/base_structure.py
src/output_routing/management.py
src/output_routing/vuln.py
src/rules/__init__.py
src/rules/rule_mgmt.py
src/rules/rule_source.py
src/utils/Conversing.py
src/utils/__init__.py
src/utils/utils.py
cryptolation-0.1.0.dist-info/METADATA
cryptolation-0.1.0.dist-info/WHEEL
cryptolation-0.1.0.dist-info/entry_points.txt
cryptolation-0.1.0.dist-info/top_level.txt
cryptolation-0.1.0.dist-info/RECORD
